LICENSE
README.md
pibe.py
setup.cfg
setup.py
pibe.egg-info/PKG-INFO
pibe.egg-info/SOURCES.txt
pibe.egg-info/dependency_links.txt
pibe.egg-info/requires.txt
pibe.egg-info/top_level.txt
pibe_ext/__init__.py
pibe_ext/api_wrapper.py
pibe_ext/appconfig.py
pibe_ext/cache.py
pibe_ext/correlation.py
pibe_ext/crud.py
pibe_ext/db.py
pibe_ext/debugger.py
pibe_ext/docs.py
pibe_ext/gl_utils.py
pibe_ext/http.py
pibe_ext/i18n.py
pibe_ext/model_validator.py
pibe_ext/redis.py
pibe_ext/rpc.py
pibe_ext/sentry.py
pibe_ext/serializer.py
pibe_ext/session.py
pibe_ext/settings.py
pibe_ext/tasks.py
pibe_ext/utils.py
pibe_ext/validator.py
pibe_ext/webhooks.py