Metadata-Version: 2.1
Name: pibe
Version: 0.32
Summary: pibe is a webob router.
Home-page: https://github.com/luismsmendonca/pibe
Download-URL: https://github.com/luismsmendonca/pibe/archive/refs/tags/v0.32.tar.gz
Author: Luis Mendonca
Author-email: luismsmendonca@gmail.com
License: MIT
Keywords: webob,router
Classifier: Development Status :: 5 - Production/Stable
Classifier: Intended Audience :: Developers
Classifier: Topic :: Software Development :: Build Tools
Classifier: License :: OSI Approved :: MIT License
Classifier: Programming Language :: Python :: 3
Classifier: Programming Language :: Python :: 3.4
Classifier: Programming Language :: Python :: 3.5
Classifier: Programming Language :: Python :: 3.6
Classifier: Programming Language :: Python :: 3.7
Classifier: Programming Language :: Python :: 3.8
Classifier: Programming Language :: Python :: 3.9
Classifier: Programming Language :: Python :: 3.10
Classifier: Programming Language :: Python :: 3.11
Classifier: Programming Language :: Python :: Implementation :: CPython
Classifier: Programming Language :: Python :: Implementation :: PyPy
Provides-Extra: testing
License-File: LICENSE
